parameters/__init__.py
parameters/export.py
parameters/random.py
parameters/validators.py
smttask/__init__.py
smttask/_utils.py
smttask/_version.py
smttask/base.py
smttask/config.py
smttask/decorators.py
smttask/examples.py
smttask/hashing.py
smttask/iotools.py
smttask/multiprocessing.py
smttask/networkx.py
smttask/param_utils.py
smttask/task_filters.py
smttask/task_generators.py
smttask/task_types.py
smttask/tqdm.py
smttask/typing.py
smttask/ui.py
smttask/utils.py
smttask/workflows.py
smttask/view/README.md
smttask/view/__init__.py
smttask/view/config.py
smttask/view/recordfilter.py
smttask/view/recordstoreview.py
smttask/view/recordview.py
smttask/view/utils.py
sumatra/__init__.py
sumatra/commands.py
sumatra/core.py
sumatra/decorators.py
sumatra/launch.py
sumatra/parameters.py
sumatra/pfi.py
sumatra/programs.py
sumatra/projects.py
sumatra/records.py
sumatra/tee.py
sumatra/users.py
sumatra/datastore/__init__.py
sumatra/datastore/archivingfs.py
sumatra/datastore/base.py
sumatra/datastore/davfs.py
sumatra/datastore/filesystem.py
sumatra/datastore/mirroredfs.py
sumatra/dependency_finder/__init__.py
sumatra/dependency_finder/core.py
sumatra/dependency_finder/genesis.py
sumatra/dependency_finder/matlab.py
sumatra/dependency_finder/neuron.py
sumatra/dependency_finder/python.py
sumatra/dependency_finder/r.py
sumatra/external_scripts/script_introspect.R
sumatra/formatting/__init__.py
sumatra/formatting/latex_template.tex
sumatra/publishing/__init__.py
sumatra/publishing/utils.py
sumatra/publishing/latex/__init__.py
sumatra/publishing/latex/example.tex
sumatra/publishing/latex/includefigure.py
sumatra/publishing/latex/sumatra.sty
sumatra/publishing/sphinxext/__init__.py
sumatra/publishing/sphinxext/sumatra_rst.py
sumatra/recordstore/__init__.py
sumatra/recordstore/base.py
sumatra/recordstore/http_store.py
sumatra/recordstore/serialization.py
sumatra/recordstore/shelve_store.py
sumatra/recordstore/django_store/__init__.py
sumatra/recordstore/django_store/models.py
smttask-0.2.0.dist-info/METADATA
smttask-0.2.0.dist-info/WHEEL
smttask-0.2.0.dist-info/entry_points.txt
smttask-0.2.0.dist-info/top_level.txt
smttask-0.2.0.dist-info/RECORD
