Metadata-Version: 2.1
Name: smttask
Version: 0.2.0
Summary: Task wrapper for the Sumatra API
Author-email: Alexandre René <arene010@uottawa.ca>
License: MIT
Project-URL: Documentation, https://sumatratask.readthedocs.io/
Project-URL: Bug Tracker, https://github.com/alcrene/smttask/issues
Project-URL: Source, https://github.com/alcrene/smttask
Classifier: Development Status :: 4 - Beta
Classifier: Intended Audience :: Science/Research
Classifier: License :: OSI Approved :: MIT License
Classifier: Programming Language :: Python :: 3
Classifier: Programming Language :: Python :: 3 :: Only
Classifier: Topic :: Scientific/Engineering
Requires-Python: >=3.7
Requires-Dist: pydantic
Requires-Dist: numpy
Requires-Dist: pandas
Requires-Dist: scityping >=v0.6.4rc4
Requires-Dist: click >=7.1
Requires-Dist: tabulate
Requires-Dist: collections-extended
Requires-Dist: tqdm >=4.62
Requires-Dist: reorder-editable
Requires-Dist: rich
Requires-Dist: GitPython
Requires-Dist: valconfig
Requires-Dist: dill
Provides-Extra: test
Requires-Dist: pytest ; extra == 'test'
Requires-Dist: scipy ; extra == 'test'
Provides-Extra: viz
Requires-Dist: networkx ; extra == 'viz'
Requires-Dist: holoviews ; extra == 'viz'
Requires-Dist: bokeh ; extra == 'viz'
